LICENSE.m2crypto
LICENSE.openssl
MANIFEST.in
README.rst
setup.py
M2Crypto/ASN1.py
M2Crypto/AuthCookie.py
M2Crypto/BIO.py
M2Crypto/BN.py
M2Crypto/DH.py
M2Crypto/DSA.py
M2Crypto/EC.py
M2Crypto/EVP.py
M2Crypto/Engine.py
M2Crypto/Err.py
M2Crypto/RC4.py
M2Crypto/RSA.py
M2Crypto/Rand.py
M2Crypto/SMIME.py
M2Crypto/X509.py
M2Crypto/__init__.py
M2Crypto/__m2crypto.py
M2Crypto/__m2crypto.pyc
M2Crypto/__m2crypto.pyd
M2Crypto/callback.py
M2Crypto/ftpslib.py
M2Crypto/httpslib.py
M2Crypto/libeay32.dll
M2Crypto/m2.py
M2Crypto/m2urllib.py
M2Crypto/m2urllib2.py
M2Crypto/m2xmlrpclib.py
M2Crypto/ssleay32.dll
M2Crypto/threading.py
M2Crypto/util.py
M2Crypto/PGP/PublicKey.py
M2Crypto/PGP/PublicKeyRing.py
M2Crypto/PGP/RSA.py
M2Crypto/PGP/__init__.py
M2Crypto/PGP/constants.py
M2Crypto/PGP/packet.py
M2Crypto/SSL/Checker.py
M2Crypto/SSL/Cipher.py
M2Crypto/SSL/Connection.py
M2Crypto/SSL/Context.py
M2Crypto/SSL/SSLServer.py
M2Crypto/SSL/Session.py
M2Crypto/SSL/TwistedProtocolWrapper.py
M2Crypto/SSL/__init__.py
M2Crypto/SSL/cb.py
M2Crypto/SSL/ssl_dispatcher.py
M2Crypto/SSL/timeout.py
M2CryptoWin32.egg-info/PKG-INFO
M2CryptoWin32.egg-info/SOURCES.txt
M2CryptoWin32.egg-info/dependency_links.txt
M2CryptoWin32.egg-info/not-zip-safe
M2CryptoWin32.egg-info/top_level.txt