Metadata-Version: 1.0
Name: M2CryptoWin32
Version: 0.21.1-2
Summary: M2Crypto for Windows (32-bit)
Home-page: https://github.com/dsoprea/M2CryptoWin32
Author: Dustin Oprea
Author-email: myselfasunder@gmail.com
License: GPL 2
Keywords: openssl ssl m2crypto
Platform: UNKNOWN
